README.md
setup.py
input_mocker/__init__.py
input_mocker.egg-info/PKG-INFO
input_mocker.egg-info/SOURCES.txt
input_mocker.egg-info/dependency_links.txt
input_mocker.egg-info/requires.txt
input_mocker.egg-info/top_level.txt