Metadata-Version: 2.1
Name: input-mocker
Version: 0.1.3
Summary: input-mocker is simple and easy-to-use tool for mocking of prompt functions.
Home-page: https://github.com/ciotto/input-mocker
Author: Ciotto
Author-email: info@ci8.it
License: MIT
Download-URL: https://github.com/ciotto/input-mocker/archive/v0.1.3.tar.gz
Keywords: tests,prompt,input,raw_input,mock
Platform: UNKNOWN
Classifier: Development Status :: 4 - Beta
Classifier: Intended Audience :: Developers
Classifier: License :: OSI Approved :: MIT License
Classifier: Natural Language :: English
Classifier: Operating System :: OS Independent
Classifier: Programming Language :: Python :: 2
Classifier: Programming Language :: Python :: 2.6
Classifier: Programming Language :: Python :: 2.7
Classifier: Programming Language :: Python :: 3
Classifier: Programming Language :: Python :: 3.4
Classifier: Programming Language :: Python :: 3.5
Classifier: Programming Language :: Python :: 3.6
Classifier: Topic :: Software Development :: Testing
